{
    "key": "group_5cabeff9de2db",
    "title": "Page Template - Landing",
    "fields": [
        {
            "key": "field_5cabf0087fe1b",
            "label": "Content Modules",
            "name": "content_modules",
            "aria-label": "",
            "type": "flexible_content",
            "instructions": "",
            "required": 0,
            "conditional_logic": 0,
            "wrapper": {
                "width": "",
                "class": "",
                "id": ""
            },
            "layouts": {
                "layout_5d8d1cdefa363": {
                    "key": "layout_5d8d1cdefa363",
                    "name": "cta_single",
                    "label": "CTA",
                    "display": "block",
                    "sub_fields": [
                        {
                            "key": "field_5d8d1ce2fa364",
                            "label": "CTA",
                            "name": "cta",
                            "aria-label": "",
                            "type": "clone",
                            "instructions": "",
                            "required": 0,
                            "conditional_logic": 0,
                            "wrapper": {
                                "width": "",
                                "class": "",
                                "id": ""
                            },
                            "clone": [
                                "group_5cabeb1f27537"
                            ],
                            "display": "seamless",
                            "layout": "block",
                            "prefix_label": 0,
                            "prefix_name": 0
                        }
                    ],
                    "min": "",
                    "max": ""
                },
                "layout_5dc9ce243188c": {
                    "key": "layout_5dc9ce243188c",
                    "name": "cta_pair",
                    "label": "CTA Pair",
                    "display": "block",
                    "sub_fields": [
                        {
                            "key": "field_5dc9ce2b3188e",
                            "label": "CTA Pair",
                            "name": "cta_pair",
                            "aria-label": "",
                            "type": "clone",
                            "instructions": "",
                            "required": 0,
                            "conditional_logic": 0,
                            "wrapper": {
                                "width": "",
                                "class": "",
                                "id": ""
                            },
                            "clone": [
                                "group_5dc9cdb7d2f4e"
                            ],
                            "display": "seamless",
                            "layout": "block",
                            "prefix_label": 0,
                            "prefix_name": 0
                        }
                    ],
                    "min": "",
                    "max": ""
                },
                "layout_5d8d1f36964d6": {
                    "key": "layout_5d8d1f36964d6",
                    "name": "cta_group",
                    "label": "CTA Group",
                    "display": "block",
                    "sub_fields": [
                        {
                            "key": "field_5d8d1fc676d83",
                            "label": "CTA Group",
                            "name": "cta_group",
                            "aria-label": "",
                            "type": "clone",
                            "instructions": "",
                            "required": 0,
                            "conditional_logic": 0,
                            "wrapper": {
                                "width": "",
                                "class": "",
                                "id": ""
                            },
                            "clone": [
                                "group_5d8d1f029d66a"
                            ],
                            "display": "seamless",
                            "layout": "block",
                            "prefix_label": 0,
                            "prefix_name": 0
                        }
                    ],
                    "min": "",
                    "max": ""
                },
                "layout_5f45314c8b4d0": {
                    "key": "layout_5f45314c8b4d0",
                    "name": "eligibility",
                    "label": "Eligibility",
                    "display": "block",
                    "sub_fields": [
                        {
                            "key": "field_5f4531528b4d1",
                            "label": "Eligibility",
                            "name": "eligibility",
                            "aria-label": "",
                            "type": "clone",
                            "instructions": "",
                            "required": 0,
                            "conditional_logic": 0,
                            "wrapper": {
                                "width": "",
                                "class": "",
                                "id": ""
                            },
                            "clone": [
                                "group_5f452ecd6404d"
                            ],
                            "display": "seamless",
                            "layout": "block",
                            "prefix_label": 0,
                            "prefix_name": 0
                        }
                    ],
                    "min": "",
                    "max": ""
                },
                "layout_5d921807dfe0c": {
                    "key": "layout_5d921807dfe0c",
                    "name": "form",
                    "label": "Form",
                    "display": "block",
                    "sub_fields": [
                        {
                            "key": "field_5d92180bdfe0d",
                            "label": "Form",
                            "name": "form",
                            "aria-label": "",
                            "type": "clone",
                            "instructions": "",
                            "required": 0,
                            "conditional_logic": 0,
                            "wrapper": {
                                "width": "",
                                "class": "",
                                "id": ""
                            },
                            "clone": [
                                "group_5ce40bf7c5d70"
                            ],
                            "display": "seamless",
                            "layout": "block",
                            "prefix_label": 0,
                            "prefix_name": 0
                        }
                    ],
                    "min": "",
                    "max": ""
                },
                "layout_5d8bad0ad9d1b": {
                    "key": "layout_5d8bad0ad9d1b",
                    "name": "text",
                    "label": "Text",
                    "display": "block",
                    "sub_fields": [
                        {
                            "key": "field_5d8bad0fd9d1c",
                            "label": "Text",
                            "name": "text",
                            "aria-label": "",
                            "type": "clone",
                            "instructions": "",
                            "required": 0,
                            "conditional_logic": 0,
                            "wrapper": {
                                "width": "",
                                "class": "",
                                "id": ""
                            },
                            "clone": [
                                "group_5d8bacd651a04"
                            ],
                            "display": "seamless",
                            "layout": "block",
                            "prefix_label": 0,
                            "prefix_name": 0
                        }
                    ],
                    "min": "",
                    "max": ""
                }
            },
            "min": "",
            "max": "",
            "button_label": "Add Module"
        }
    ],
    "location": [
        [
            {
                "param": "page_template",
                "operator": "==",
                "value": "spm-landing.php"
            }
        ]
    ],
    "menu_order": 0,
    "position": "normal",
    "style": "seamless",
    "label_placement": "top",
    "instruction_placement": "label",
    "hide_on_screen": [
        "the_content"
    ],
    "active": true,
    "description": "",
    "show_in_rest": 0,
    "modified": 1699476210
}
